{"$schema": "http://json-schema.org/draft-03/schema#", "dependencies": {"exclusiveMaximum": "maximum", "exclusiveMinimum": "minimum"}, "type": "object", "id": "http://json-schema.org/draft-03/schema#", "properties": {"maxDecimal": {"minimum": 0, "type": "number"}, "minimum": {"type": "number"}, "maxItems": {"minimum": 0, "type": "integer"}, "$schema": {"type": "string", "format": "uri"}, "exclusiveMinimum": {"default": false, "type": "boolean"}, "id": {"type": "string", "format": "uri"}, "$ref": {"type": "string", "format": "uri"}, "exclusiveMaximum": {"default": false, "type": "boolean"}, "title": {"type": "string"}, "pattern": {"type": "string", "format": "regex"}, "patternProperties": {"additionalProperties": {"$ref": "#"}, "default": {}, "type": "object"}, "extends": {"default": {}, "items": {"$ref": "#"}, "type": [{"$ref": "#"}, "array"]}, "type": {"uniqueItems": true, "items": {"type": ["string", {"$ref": "#"}]}, "default": "any", "type": ["string", "array"]}, "description": {"type": "string"}, "format": {"type": "string"}, "minLength": {"default": 0, "minimum": 0, "type": "integer"}, "enum": {"minItems": 1, "uniqueItems": true, "type": "array"}, "disallow": {"uniqueItems": true, "items": {"type": ["string", {"$ref": "#"}]}, "type": ["string", "array"]}, "divisibleBy": {"default": 1, "exclusiveMinimum": true, "minimum": 0, "type": "number"}, "dependencies": {"additionalProperties": {"items": {"type": "string"}, "type": ["string", "array", {"$ref": "#"}]}, "default": {}, "type": ["string", "array", "object"]}, "maxLength": {"type": "integer"}, "uniqueItems": {"default": false, "type": "boolean"}, "properties": {"additionalProperties": {"type": "object", "$ref": "#"}, "default": {}, "type": "object"}, "additionalItems": {"default": {}, "type": [{"$ref": "#"}, "boolean"]}, "default": {"type": "any"}, "items": {"default": {}, "items": {"$ref": "#"}, "type": [{"$ref": "#"}, "array"]}, "required": {"default": false, "type": "boolean"}, "maximum": {"type": "number"}, "minItems": {"default": 0, "minimum": 0, "type": "integer"}, "additionalProperties": {"default": {}, "type": [{"$ref": "#"}, "boolean"]}}}